data/DB_iP_not_typed.csv
data/DB_iP_typed.csv
data/DB_iP_typed_with_mass_concentration.csv
data/DB_iP_typed_with_mol_concentration.csv
data/primers.csv
insillyclo/__init__.py
insillyclo/_version.py
insillyclo/additional_exception.py
insillyclo/cli_utils.py
insillyclo/conf.py
insillyclo/data_source.py
insillyclo/digestion.py
insillyclo/dilution.py
insillyclo/gel.py
insillyclo/main.py
insillyclo/models.py
insillyclo/observer.py
insillyclo/parser.py
insillyclo/simulator.py
insillyclo/template_generator.py
insillyclo-1.0.7.dist-info/licenses/LICENSE
insillyclo-1.0.7.dist-info/METADATA
insillyclo-1.0.7.dist-info/WHEEL
insillyclo-1.0.7.dist-info/entry_points.txt
insillyclo-1.0.7.dist-info/top_level.txt
insillyclo-1.0.7.dist-info/RECORD
