Metadata-Version: 2.4
Name: insillyclo
Version: 1.0.7
Summary: A toolkit to support Golden Gate assembly, along with digestion, gel simulation, and more
Author: Gregory Batt, Bryan Brancotte, Juliette Bonche, Julien Fumey, Henri Galez
Project-URL: Homepage, https://gitlab.pasteur.fr/hub/insillyclo-cli
Project-URL: Issues, https://gitlab.pasteur.fr/hub/insillyclo-cli/issues
Classifier: Programming Language :: Python :: 3
Classifier: Operating System :: OS Independent
Requires-Python: >=3.10
License-File: LICENSE
Requires-Dist: click
Requires-Dist: pandas
Requires-Dist: xlsxwriter
Requires-Dist: openpyxl
Requires-Dist: pandas
Requires-Dist: Bio
Requires-Dist: pycairo
Requires-Dist: sbol2
Provides-Extra: dev
Requires-Dist: build; extra == "dev"
Requires-Dist: twine; extra == "dev"
Requires-Dist: coverage; extra == "dev"
Requires-Dist: black~=24.10.0; extra == "dev"
Requires-Dist: setuptools>=62.6; extra == "dev"
Dynamic: license-file
